LICENSE
MANIFEST.in
README.md
setup.py
FlatCAM.egg-info/PKG-INFO
FlatCAM.egg-info/SOURCES.txt
FlatCAM.egg-info/dependency_links.txt
FlatCAM.egg-info/requires.txt
FlatCAM.egg-info/top_level.txt
flatcam/FlatCAMApp.py
flatcam/FlatCAMCommon.py
flatcam/FlatCAMDraw.py
flatcam/FlatCAMGUI.py
flatcam/FlatCAMObj.py
flatcam/FlatCAMProcess.py
flatcam/FlatCAMShell.py
flatcam/FlatCAMTool.py
flatcam/FlatCAMVersion.py
flatcam/FlatCAMWorker.py
flatcam/GUIElements.py
flatcam/ObjectCollection.py
flatcam/ObjectUI.py
flatcam/PlotCanvas.py
flatcam/ToolDblSided.py
flatcam/ToolMeasurement.py
flatcam/ToolTransform.py
flatcam/__init__.py
flatcam/camlib.py
flatcam/svgparse.py
flatcam/termwidget.py
flatcam.egg-info/PKG-INFO
flatcam.egg-info/SOURCES.txt
flatcam.egg-info/dependency_links.txt
flatcam.egg-info/requires.txt
flatcam.egg-info/top_level.txt
flatcam/descartes/__init__.py
flatcam/descartes/patch.py
flatcam/descartes/tests.py
flatcam/tclCommands/TclCommand.py
flatcam/tclCommands/TclCommandAddCircle.py
flatcam/tclCommands/TclCommandAddPolygon.py
flatcam/tclCommands/TclCommandAddPolyline.py
flatcam/tclCommands/TclCommandAddRectangle.py
flatcam/tclCommands/TclCommandAlignDrill.py
flatcam/tclCommands/TclCommandAlignDrillGrid.py
flatcam/tclCommands/TclCommandCncjob.py
flatcam/tclCommands/TclCommandCutout.py
flatcam/tclCommands/TclCommandDelete.py
flatcam/tclCommands/TclCommandDrillcncjob.py
flatcam/tclCommands/TclCommandExportGcode.py
flatcam/tclCommands/TclCommandExportSVG.py
flatcam/tclCommands/TclCommandExteriors.py
flatcam/tclCommands/TclCommandFollow.py
flatcam/tclCommands/TclCommandGeoCutout.py
flatcam/tclCommands/TclCommandGeoUnion.py
flatcam/tclCommands/TclCommandGetNames.py
flatcam/tclCommands/TclCommandGetSys.py
flatcam/tclCommands/TclCommandImportSvg.py
flatcam/tclCommands/TclCommandInteriors.py
flatcam/tclCommands/TclCommandIsolate.py
flatcam/tclCommands/TclCommandJoinExcellon.py
flatcam/tclCommands/TclCommandJoinGeometry.py
flatcam/tclCommands/TclCommandListSys.py
flatcam/tclCommands/TclCommandMillHoles.py
flatcam/tclCommands/TclCommandMirror.py
flatcam/tclCommands/TclCommandNew.py
flatcam/tclCommands/TclCommandNewGeometry.py
flatcam/tclCommands/TclCommandOffset.py
flatcam/tclCommands/TclCommandOpenExcellon.py
flatcam/tclCommands/TclCommandOpenGCode.py
