Metadata-Version: 1.1
Name: flatcam
Version: 0.8.5
Summary: 2D Computer-Aided PCB Manufacturing
Home-page: http://flatcam.org/
Author: Juan Pablo Caram
Author-email: brainstorm+flatcamfork@nopcode.org
License: MIT
Platform: UNKNOWN
Classifier: Development Status :: 4 - Beta
Classifier: Environment :: MacOS X
Classifier: Environment :: X11 Applications :: Qt
Classifier: Intended Audience :: Manufacturing
Classifier: License :: OSI Approved :: MIT License
Classifier: Programming Language :: Python :: 3
Classifier: Topic :: Scientific/Engineering :: Electronic Design Automation (EDA)
